README.md
setup.py
multable/__init__.py
multable.egg-info/PKG-INFO
multable.egg-info/SOURCES.txt
multable.egg-info/dependency_links.txt
multable.egg-info/top_level.txt