Metadata-Version: 2.1
Name: multable
Version: 0.0.1
Summary: 调用此方法可打印9*9乘法表
Home-page: https://github.com/tanxinyue/multable
Author: 李厚奇
Author-email: 884359533@qq.com
License: UNKNOWN
Platform: UNKNOWN
Classifier: Programming Language :: Python :: 3
Classifier: License :: OSI Approved :: MIT License
Classifier: Operating System :: OS Independent
Requires-Python: >=3.7
